Metadata-Version: 2.4
Name: dppd
Version: 0.31
Summary: A pythonic dplyr clone
Author-email: Florian Finkernagel <finkernagel@imt.uni-marburg.de>
License: The MIT License (MIT)
Project-URL: Documentation, https://dppd.readthedocs.io/en/latest/
Project-URL: Repository, https://github.com/TyberiusPrime/dppd
Requires-Python: >=3.9
License-File: LICENSE.txt
License-File: AUTHORS.rst
Requires-Dist: natsort
Requires-Dist: numpy
Requires-Dist: pandas>=2
Requires-Dist: wrapt
Provides-Extra: dev
Requires-Dist: build; extra == "dev"
Requires-Dist: numpydoc; extra == "dev"
Requires-Dist: plotnine; extra == "dev"
Requires-Dist: pytest; extra == "dev"
Requires-Dist: pytest-cov; extra == "dev"
Requires-Dist: sphinx; extra == "dev"
Requires-Dist: sphinx-bootstrap-theme; extra == "dev"
Dynamic: license-file
